Dali/__init__.py
Dali/algorithms.py
Dali/color.py
Dali/fit.py
Dali/fonts.py
Dali/latex.py
Dali/plotting.py
Dali/stats.py
dali_lib-1.0.8.dist-info/METADATA
dali_lib-1.0.8.dist-info/WHEEL
dali_lib-1.0.8.dist-info/top_level.txt
dali_lib-1.0.8.dist-info/RECORD
