Metadata-Version: 2.1
Name: dali_lib
Version: 1.0.8
Requires-Dist: numpy
Requires-Dist: pandas
Requires-Dist: scipy
Requires-Dist: matplotlib
Requires-Dist: jinja2
